twinfield/__init__.py
twinfield/api.py
twinfield/browse.py
twinfield/core.py
twinfield/deleted.py
twinfield/dimensions.py
twinfield/exceptions.py
twinfield/login.py
twinfield/messages.py
twinfield/metadata.py
twinfield/offices.py
twinfield/tests/__init__.py
twinfield/tests/test_twinfield.py
twinfield-2.1.3.dist-info/licenses/LICENSE
twinfield-2.1.3.dist-info/METADATA
twinfield-2.1.3.dist-info/WHEEL
twinfield-2.1.3.dist-info/top_level.txt
twinfield-2.1.3.dist-info/RECORD
