Metadata-Version: 2.4
Name: twinfield
Version: 2.1.3
Summary: Read and insert data using the Twinfield API.
Home-page: https://github.com/zypp-io/twinfield
Author: Zypp
Author-email: hello@zypp.io
Project-URL: Bug Reports, https://github.com/zypp-io/twinfield/issues
Project-URL: Source, https://github.com/zypp-io/twinfield
Keywords: python,twinfield,API
Classifier: Programming Language :: Python :: 3
Classifier: License :: OSI Approved :: MIT License
Classifier: Operating System :: OS Independent
Requires-Python: >=3.7
License-File: LICENSE
Requires-Dist: pandas>=1.4.3
Requires-Dist: requests~=2.31.0
Requires-Dist: SQLAlchemy>=1.4.22
Requires-Dist: tqdm~=4.66.1
Dynamic: author
Dynamic: author-email
Dynamic: classifier
Dynamic: description
Dynamic: description-content-type
Dynamic: home-page
Dynamic: keywords
Dynamic: license-file
Dynamic: project-url
Dynamic: requires-dist
Dynamic: requires-python
Dynamic: summary
